Q3/dmem.v
module dmem (
    input clk, we,
    input [31:0] a, wd,
    output [31:0] rd
);
    reg [31:0] RAM[0:63]; // 64-word memory

    assign rd = RAM[a[31:2]];

    always @(posedge clk) begin
        if (we) RAM[a[31:2]] <= wd;
    end
endmodule

Q1/imem.v
module imem (
    input [31:0] a,
    output [31:0] rd
);
    reg [31:0] ROM[0:63];

    initial begin
        $readmemh("memfile.hex", ROM);
    end

    assign rd = ROM[a[31:2]];
endmodule

Q1/alu.v
module alu (
    input [31:0] a, b,
    input [2:0] alucontrol,
    output reg [31:0] result,
    output zero
);
    always @(*) begin
        case (alucontrol)
            3'b000: result = a + b;
            3'b001: result = a - b;
            3'b010: result = a & b;
            3'b011: result = a | b;
            3'b101: result = ($signed(a) < $signed(b)) ? 32'd1 : 32'd0; // slt
            default: result = 32'bx;
        endcase
    end
    assign zero = (result == 32'b0);
endmodule

Q2/extend.v
module extend (
    input [31:7] instr,
    input [1:0] immsrc,
    output reg [31:0] immext
);
    always @(*) begin
        case (immsrc)
            2'b00: immext = {{20{instr[31]}}, instr[31:20]}; // I-type
            2'b01: immext = {{20{instr[31]}}, instr[31:25], instr[11:7]}; // S-type
            2'b10: immext = {{20{instr[31]}}, instr[7], instr[30:25], instr[11:8], 1'b0}; // B-type
            2'b11: immext = {{12{instr[31]}}, instr[19:12], instr[20], instr[30:21], 1'b0}; // J-type
            default: immext = 32'bx;
        endcase
    end
endmodule

Q3/regfile.v
module regfile (
    input clk,
    input we3,
    input [4:0] a1, a2, a3,
    input [31:0] wd3,
    output [31:0] rd1, rd2
);
    reg [31:0] rf[31:0];

    always @(posedge clk) begin
        if (we3 && a3 != 0) rf[a3] <= wd3;
    end

    assign rd1 = (a1 != 0) ? rf[a1] : 32'b0;
    assign rd2 = (a2 != 0) ? rf[a2] : 32'b0;
endmodule

Q2/datapath.v
module datapath (
    input clk, reset,
    input [1:0] resultsrc,
    input pcsrc, alusrc,
    input regwrite,
    input [1:0] immsrc,
    input [2:0] alucontrol,
    output zero,
    output reg [31:0] pc,
    input [31:0] instr,
    output [31:0] aluout, writedata,
    input [31:0] readdata
);
    wire [31:0] pcnext, pcplus4, pctarget;
    wire [31:0] immext;
    wire [31:0] srca, srcb;
    wire [31:0] result;

    assign pcplus4 = pc + 4;
    assign pctarget = pc + immext;
    assign pcnext = pcsrc ? pctarget : pcplus4;

    always @(posedge clk or posedge reset) begin
        if (reset) pc <= 32'b0;
        else pc <= pcnext;
    end

    regfile rf (
        .clk(clk),
        .we3(regwrite),
        .a1(instr[19:15]),
        .a2(instr[24:20]),
        .a3(instr[11:7]),
        .wd3(result),
        .rd1(srca),
        .rd2(writedata)
    );

    extend ext (
        .instr(instr[31:7]),
        .immsrc(immsrc),
        .immext(immext)
    );

    assign srcb = alusrc ? immext : writedata;

    alu alu_inst (
        .a(srca),
        .b(srcb),
        .alucontrol(alucontrol),
        .result(aluout),
        .zero(zero)
    );

    assign result = (resultsrc == 2'b00) ? aluout :
                    (resultsrc == 2'b01) ? readdata :
                    (resultsrc == 2'b10) ? pcplus4 : 32'bx;

endmodule

Q1/controller.v
module controller (
    input [6:0] op,
    input [2:0] funct3,
    input funct7_5,
    input zero,
    output resultsrc_0, resultsrc_1,
    output memwrite,
    output pcsrc, alusrc,
    output regwrite, jump,
    output [1:0] immsrc,
    output [2:0] alucontrol
);
    wire [1:0] aluop;
    wire branch;
    
    maindec md (
        .op(op),
        .resultsrc({resultsrc_1, resultsrc_0}),
        .memwrite(memwrite),
        .branch(branch),
        .alusrc(alusrc),
        .regwrite(regwrite),
        .jump(jump),
        .immsrc(immsrc),
        .aluop(aluop)
    );
    
    aludec ad (
        .opb5(op[5]),
        .funct3(funct3),
        .funct7_5(funct7_5),
        .aluop(aluop),
        .alucontrol(alucontrol)
    );
    
    assign pcsrc = jump | (branch & zero);
endmodule

module maindec (
    input [6:0] op,
    output reg [1:0] resultsrc,
    output reg memwrite,
    output reg branch,
    output reg alusrc,
    output reg regwrite,
    output reg jump,
    output reg [1:0] immsrc,
    output reg [1:0] aluop
);
    always @(*) begin
        case (op)
            7'b0000011: begin // lw
                regwrite = 1; immsrc = 2'b00; alusrc = 1; memwrite = 0;
                resultsrc = 2'b01; branch = 0; aluop = 2'b00; jump = 0;
            end
            7'b0100011: begin // sw
                regwrite = 0; immsrc = 2'b01; alusrc = 1; memwrite = 1;
                resultsrc = 2'bxx; branch = 0; aluop = 2'b00; jump = 0;
            end
            7'b0110011: begin // R-type
                regwrite = 1; immsrc = 2'bxx; alusrc = 0; memwrite = 0;
                resultsrc = 2'b00; branch = 0; aluop = 2'b10; jump = 0;
            end
            7'b1100011: begin // beq
                regwrite = 0; immsrc = 2'b10; alusrc = 0; memwrite = 0;
                resultsrc = 2'bxx; branch = 1; aluop = 2'b01; jump = 0;
            end
            7'b0010011: begin // I-type ALU
                regwrite = 1; immsrc = 2'b00; alusrc = 1; memwrite = 0;
                resultsrc = 2'b00; branch = 0; aluop = 2'b10; jump = 0; 
            end
            7'b1101111: begin // jal
                regwrite = 1; immsrc = 2'b11; alusrc = 1'bx; memwrite = 0;
                resultsrc = 2'b10; branch = 0; aluop = 2'bxx; jump = 1;
            end
            default: begin
                regwrite = 0; immsrc = 2'b00; alusrc = 0; memwrite = 0;
                resultsrc = 2'b00; branch = 0; aluop = 2'b00; jump = 0;
            end
        endcase
    end
endmodule

module aludec (
    input opb5,
    input [2:0] funct3,
    input funct7_5,
    input [1:0] aluop,
    output reg [2:0] alucontrol
);
    always @(*) begin
        case (aluop)
            2'b00: alucontrol = 3'b000; // add
            2'b01: alucontrol = 3'b001; // sub
            2'b10: begin // R-type or I-type ALU
                case (funct3)
                    3'b000: begin
                        if ({opb5, funct7_5} == 2'b11) alucontrol = 3'b001; // sub
                        else alucontrol = 3'b000; // add
                    end
                    3'b010: alucontrol = 3'b101; // slt, slti
                    3'b110: alucontrol = 3'b011; // or, ori
                    3'b111: alucontrol = 3'b010; // and, andi
                    default: alucontrol = 3'bxxx;
                endcase
            end
            default: alucontrol = 3'bxxx;
        endcase
    end
endmodule

Q2/riscv_core.v
module riscv_core (
    input clk, reset,
    output [31:0] writedata, dataadr,
    output memwrite
);
    wire [31:0] pc, instr, readdata;
    wire [1:0] resultsrc;
    wire pcsrc, alusrc, regwrite, jump, zero;
    wire [1:0] immsrc;
    wire [2:0] alucontrol;

    controller c (
        .op(instr[6:0]),
        .funct3(instr[14:12]),
        .funct7_5(instr[30]),
        .zero(zero),
        .resultsrc_0(resultsrc[0]),
        .resultsrc_1(resultsrc[1]),
        .memwrite(memwrite),
        .pcsrc(pcsrc),
        .alusrc(alusrc),
        .regwrite(regwrite),
        .jump(jump),
        .immsrc(immsrc),
        .alucontrol(alucontrol)
    );

    datapath dp (
        .clk(clk),
        .reset(reset),
        .resultsrc(resultsrc),
        .pcsrc(pcsrc),
        .alusrc(alusrc),
        .regwrite(regwrite),
        .immsrc(immsrc),
        .alucontrol(alucontrol),
        .zero(zero),
        .pc(pc),
        .instr(instr),
        .aluout(dataadr),
        .writedata(writedata),
        .readdata(readdata)
    );

    imem imem_inst (
        .a(pc),
        .rd(instr)
    );

    dmem dmem_inst (
        .clk(clk),
        .we(memwrite),
        .a(dataadr),
        .wd(writedata),
        .rd(readdata)
    );
endmodule

Q3/tb_q1.v
`timescale 1ns/1ps

// ============================================================================
// tb_q1.v  –  Full Testbench for RISC-V Single-Cycle Processor (Q1)
// Tests ALL 13 supported instructions:
//   R-type : add, sub, slt, or, and
//   I-type : addi, slti, ori, andi, lw
//   S-type : sw
//   B-type : beq
//   J-type : jal
//
// The test program is loaded from memfile.hex.
// After execution, the testbench reads back values stored in data memory
// by the program and compares them against expected results.
// ============================================================================

module tb_q1;

    // ------------------------------------------------------------------
    // Signals
    // ------------------------------------------------------------------
    reg         clk;
    reg         reset;
    wire [31:0] writedata, dataadr;
    wire        memwrite;

    // ------------------------------------------------------------------
    // DUT instantiation
    // ------------------------------------------------------------------
    riscv_core dut (
        .clk       (clk),
        .reset     (reset),
        .writedata (writedata),
        .dataadr   (dataadr),
        .memwrite  (memwrite)
    );

    // ------------------------------------------------------------------
    // Clock generation – 10 ns period (100 MHz)
    // ------------------------------------------------------------------
    always begin
        clk <= 1; #5;
        clk <= 0; #5;
    end

    // ------------------------------------------------------------------
    // Test counters
    // ------------------------------------------------------------------
    integer pass_count;
    integer fail_count;
    integer test_num;

    // ------------------------------------------------------------------
    // Task: check a data-memory word against an expected value
    // ------------------------------------------------------------------
    task check_dmem;
        input [31:0] addr;       // byte address
        input [31:0] expected;
        input [255:0] test_name; // label for display
        begin
            test_num = test_num + 1;
            if (dut.dmem_inst.RAM[addr[31:2]] === expected) begin
                $display("  [PASS] Test %0d : %-20s | dmem[%0d] = 0x%08h (expected 0x%08h)",
                         test_num, test_name, addr, expected, expected);
                pass_count = pass_count + 1;
            end else begin
                $display("  [FAIL] Test %0d : %-20s | dmem[%0d] = 0x%08h (expected 0x%08h)",
                         test_num, test_name, addr,
                         dut.dmem_inst.RAM[addr[31:2]], expected);
                fail_count = fail_count + 1;
            end
        end
    endtask

    // ------------------------------------------------------------------
    // Monitor: trace every memory write as it happens
    // ------------------------------------------------------------------
    always @(negedge clk) begin
        if (memwrite)
            $display("  [WRITE] cycle=%0t : MEM[0x%08h] <= 0x%08h",
                     $time, dataadr, writedata);
    end

    // ------------------------------------------------------------------
    // Main stimulus
    // ------------------------------------------------------------------
    initial begin
        // VCD dump for GTKWave
        $dumpfile("tb_q1.vcd");
        $dumpvars(0, tb_q1);

        pass_count = 0;
        fail_count = 0;
        test_num   = 0;

        // ---- Apply reset ----
        reset <= 1;
        #22;
        reset <= 0;

        // ---- Let program execute ----
        // The memfile.hex program has ~30 instructions.
        // 30 instructions × 10 ns/cycle = 300 ns. Allow generous margin.
        #500;

        // ==============================================================
        // Verify results stored in data memory by the test program
        // ==============================================================
        $display("");
        $display("==========================================================");
        $display("  RISC-V Single-Cycle Processor – Testbench Results (Q1)");
        $display("==========================================================");
        $display("");

        // ---- addi  : x1 = 10                  → store x1 to dmem[100] ----
        check_dmem(100, 32'd10,   "addi            ");

        // ---- addi  : x2 = 15                  → store x2 to dmem[104] ----
        check_dmem(104, 32'd15,   "addi            ");

        // ---- add   : x3 = x1 + x2 = 25        → store x3 to dmem[108] ----
        check_dmem(108, 32'd25,   "add             ");

        // ---- sub   : x4 = x2 - x1 = 5         → store x4 to dmem[112] ----
        check_dmem(112, 32'd5,    "sub             ");

        // ---- and   : x5 = x1 & x2 = 10&15=10  → store x5 to dmem[116] ----
        check_dmem(116, 32'd10,   "and             ");

        // ---- or    : x6 = x1 | x2 = 10|15=15  → store x6 to dmem[120] ----
        check_dmem(120, 32'd15,   "or              ");

        // ---- slt   : x7 = (x1 < x2) = 1       → store x7 to dmem[124] ----
        check_dmem(124, 32'd1,    "slt             ");

        // ---- andi  : x8 = x1 & 0x7 = 10&7=2   → store x8 to dmem[128] ----
        check_dmem(128, 32'd2,    "andi            ");

        // ---- ori   : x9 = x1 | 0x5 = 10|5=15  → store x9 to dmem[132] ----
        check_dmem(132, 32'd15,   "ori             ");

        // ---- slti  : x10 = (x1 < 20) = 1      → store x10 to dmem[136] ----
        check_dmem(136, 32'd1,    "slti            ");

        // ---- sw/lw : store x3(25) to dmem[200], load back into x11
        //              → store x11 to dmem[140], expect 25 ----
        check_dmem(140, 32'd25,   "sw & lw         ");

        // ---- beq   : x12 = 99 if beq NOT taken (x1 != x2)
        //              beq skips over "addi x12,x0,99" → x12 should be 0
        //              then x12 = 42 after the branch target
        //              → store x12 to dmem[144], expect 42 ----
        check_dmem(144, 32'd42,   "beq (not taken) ");

        // ---- jal   : x14 = return address (PC+4 at jal site)
        //              at the jal target: x13 = 77
        //              → store x13 to dmem[148], expect 77 ----
        check_dmem(148, 32'd77,   "jal             ");

        // ==============================================================
        // Summary
        // ==============================================================
        $display("");
        $display("----------------------------------------------------------");
        $display("  Total: %0d tests | Passed: %0d | Failed: %0d",
                 pass_count + fail_count, pass_count, fail_count);
        $display("----------------------------------------------------------");

        if (fail_count == 0)
            $display("  >>> ALL TESTS PASSED – Simulation succeeded <<<");
        else
            $display("  >>> SOME TESTS FAILED – Simulation FAILED <<<");

        $display("==========================================================");
        $display("");

        $finish;
    end

endmodule

Q1/tb_q1.vcd
$date
	Thu Apr 30 12:50:10 2026
$end
$version
	Icarus Verilog
$end
$timescale
	1ps
$end
$scope module tb_q1 $end
$var wire 32 ! writedata [31:0] $end
$var wire 1 " memwrite $end
$var wire 32 # dataadr [31:0] $end
$var reg 1 $ clk $end
$var reg 1 % reset $end
$var integer 32 & fail_count [31:0] $end
$var integer 32 ' pass_count [31:0] $end
$var integer 32 ( test_num [31:0] $end
$scope module dut $end
$var wire 1 $ clk $end
$var wire 1 % reset $end
$var wire 1 ) zero $end
$var wire 32 * writedata [31:0] $end
$var wire 2 + resultsrc [1:0] $end
$var wire 1 , regwrite $end
$var wire 32 - readdata [31:0] $end
$var wire 1 . pcsrc $end
$var wire 32 / pc [31:0] $end
$var wire 1 " memwrite $end
$var wire 1 0 jump $end
$var wire 32 1 instr [31:0] $end
$var wire 2 2 immsrc [1:0] $end
$var wire 32 3 dataadr [31:0] $end
$var wire 1 4 alusrc $end
$var wire 3 5 alucontrol [2:0] $end
$scope module c $end
$var wire 3 6 funct3 [2:0] $end
$var wire 1 7 funct7_5 $end
$var wire 7 8 op [6:0] $end
$var wire 1 . pcsrc $end
$var wire 1 ) zero $end
$var wire 1 9 resultsrc_1 $end
$var wire 1 : resultsrc_0 $end
$var wire 1 , regwrite $end
$var wire 1 " memwrite $end
$var wire 1 0 jump $end
$var wire 2 ; immsrc [1:0] $end
$var wire 1 < branch $end
$var wire 1 4 alusrc $end
$var wire 2 = aluop [1:0] $end
$var wire 3 > alucontrol [2:0] $end
$scope module ad $end
$var wire 3 ? funct3 [2:0] $end
$var wire 1 7 funct7_5 $end
$var wire 1 @ opb5 $end
$var wire 2 A aluop [1:0] $end
$var reg 3 B alucontrol [2:0] $end
$upscope $end
$scope module md $end
$var wire 7 C op [6:0] $end
$var reg 2 D aluop [1:0] $end
$var reg 1 4 alusrc $end
$var reg 1 < branch $end
$var reg 2 E immsrc [1:0] $end
$var reg 1 0 jump $end
$var reg 1 " memwrite $end
$var reg 1 , regwrite $end
$var reg 2 F resultsrc [1:0] $end
$upscope $end
$upscope $end
$scope module dmem_inst $end
$var wire 1 $ clk $end
$var wire 32 G rd [31:0] $end
$var wire 1 " we $end
$var wire 32 H wd [31:0] $end
$var wire 32 I a [31:0] $end
$upscope $end
$scope module dp $end
$var wire 3 J alucontrol [2:0] $end
$var wire 1 4 alusrc $end
$var wire 1 $ clk $end
$var wire 2 K immsrc [1:0] $end
$var wire 1 . pcsrc $end
$var wire 32 L readdata [31:0] $end
$var wire 1 , regwrite $end
$var wire 1 % reset $end
$var wire 2 M resultsrc [1:0] $end
$var wire 1 ) zero $end
$var wire 32 N writedata [31:0] $end
$var wire 32 O srcb [31:0] $end
$var wire 32 P srca [31:0] $end
$var wire 32 Q result [31:0] $end
$var wire 32 R pctarget [31:0] $end
$var wire 32 S pcplus4 [31:0] $end
$var wire 32 T pcnext [31:0] $end
$var wire 32 U instr [31:0] $end
$var wire 32 V immext [31:0] $end
$var wire 32 W aluout [31:0] $end
$var reg 32 X pc [31:0] $end
$scope module alu_inst $end
$var wire 3 Y alucontrol [2:0] $end
$var wire 32 Z b [31:0] $end
$var wire 1 ) zero $end
$var wire 32 [ a [31:0] $end
$var reg 32 \ result [31:0] $end
$upscope $end
$scope module ext $end
$var wire 2 ] immsrc [1:0] $end
$var wire 25 ^ instr [31:7] $end
$var reg 32 _ immext [31:0] $end
$upscope $end
$scope module rf $end
$var wire 5 ` a1 [4:0] $end
$var wire 5 a a2 [4:0] $end
$var wire 5 b a3 [4:0] $end
$var wire 1 $ clk $end
$var wire 32 c wd3 [31:0] $end
$var wire 1 , we3 $end
$var wire 32 d rd2 [31:0] $end
$var wire 32 e rd1 [31:0] $end
$upscope $end
$upscope $end
$scope module imem_inst $end
$var wire 32 f a [31:0] $end
$var wire 32 g rd [31:0] $end
$upscope $end
$upscope $end
$scope task check_dmem $end
$var reg 32 h addr [31:0] $end
$var reg 32 i expected [31:0] $end
$var reg 256 j test_name [255:0] $end
$upscope $end
$upscope $end
$enddefinitions $end
$comment Show the parameter values. $end
$dumpall
$end
#0
$dumpvars
bx j
bx i
bx h
b101000000000000010010011 g
b0 f
b0 e
bx d
b1010 c
b1 b
b1010 a
b0 `
b1010 _
b10100000000000001 ^
b0 ]
b1010 \
b0 [
b1010 Z
b0 Y
b0 X
b1010 W
b1010 V
b101000000000000010010011 U
b100 T
b100 S
b1010 R
b1010 Q
b0 P
b1010 O
bx N
b0 M
bx L
b0 K
b0 J
b1010 I
bx H
bx G
b0 F
b0 E
b10 D
b10011 C
b0 B
b10 A
0@
b0 ?
b0 >
b10 =
0<
b0 ;
0:
09
b10011 8
07
b0 6
b0 5
14
b1010 3
b0 2
b101000000000000010010011 1
00
b0 /
0.
bx -
1,
b0 +
bx *
0)
b0 (
b0 '
b0 &
1%
1$
b1010 #
0"
bx !
$end
#5000
0$
#10000
1$
#15000
0$
#20000
1$
#22000
0%
#25000
0$
#30000
b1111 Q
b1111 c
b1111 #
b1111 3
b1111 I
b1111 W
b1111 \
b1111 O
b1111 Z
b1111 V
b1111 _
b11110000000000010 ^
b10 b
b1111 a
b1000 T
b111100000000000100010011 1
b111100000000000100010011 U
b111100000000000100010011 g
b1000 S
b10011 R
b100 /
b100 X
b100 f
1$
#35000
0$
#40000
b11001 Q
b11001 c
0)
b11001 #
b11001 3
b11001 I
b11001 W
b11001 \
b1111 !
b1111 *
b1111 H
b1111 N
b1111 d
b1010 P
b1010 [
b1010 e
b1111 O
b1111 Z
bx V
bx _
1@
04
bx 2
bx ;
bx E
bx K
bx ]
b100000100000011 ^
b11 b
b10 a
b1 `
b110011 8
b110011 C
b1100 T
b1000001000000110110011 1
b1000001000000110110011 U
b1000001000000110110011 g
b1100 S
bx R
b1000 /
b1000 X
b1000 f
1$
#45000
0$
#50000
b1010 O
b1010 Z
0)
b101 Q
b101 c
b1010 !
b1010 *
b1010 H
b1010 N
b1010 d
b1111 P
b1111 [
b1111 e
b101 #
b101 3
b101 I
b101 W
b101 \
b1 5
b1 >
b1 B
b1 J
b1 Y
b100000000010001000000100 ^
b100 b
b1 a
b10 `
17
b10000 T
b1000000000100010000001000110011 1
b1000000000100010000001000110011 U
b1000000000100010000001000110011 g
b10000 S
b1100 /
b1100 X
b1100 f
1$
#55000
0$
#60000
b1111 O
b1111 Z
b1010 Q
b1010 c
b1111 !
b1111 *
b1111 H
b1111 N
b1111 d
b1010 P
b1010 [
b1010 e
b1010 #
b1010 3
b1010 I
b1010 W
b1010 \
b10 5
b10 >
b10 B
b10 J
b10 Y
b100000111100101 ^
b101 b
b10 a
b1 `
07
b111 6
b111 ?
b10100 T
b1000001111001010110011 1
b1000001111001010110011 U
b1000001111001010110011 g
b10100 S
b10000 /
b10000 X
b10000 f
1$
#65000
0$
#70000
b1111 Q
b1111 c
b1111 #
b1111 3
b1111 I
b1111 W
b1111 \
b11 5
b11 >
b11 B
b11 J
b11 Y
b100000111000110 ^
b110 b
b110 6
b110 ?
b11000 T
b1000001110001100110011 1
b1000001110001100110011 U
b1000001110001100110011 g
b11000 S
b10100 /
b10100 X
b10100 f
1$
#75000
0$
#80000
b1 Q
b1 c
b1 #
b1 3
b1 I
b1 W
b1 \
b101 5
b101 >
b101 B
b101 J
b101 Y
b100000101000111 ^
b111 b
b10 6
b10 ?
b11100 T
b1000001010001110110011 1
b1000001010001110110011 U
b1000001010001110110011 g
b11100 S
b11000 /
b11000 X
b11000 f
1$
#85000
0$
#90000
b10 Q
b10 c
b1 !
b1 *
b1 H
b1 N
b1 d
b10 #
b10 3
b10 I
b10 W
b10 \
b111 O
b111 Z
b100011 R
b111 V
b111 _
b10 5
b10 >
b10 B
b10 J
b10 Y
0@
14
b0 2
b0 ;
b0 E
b0 K
b0 ]
b1110000111101000 ^
b1000 b
b111 a
b111 6
b111 ?
b10011 8
b10011 C
b100000 T
b11100001111010000010011 1
b11100001111010000010011 U
b11100001111010000010011 g
b100000 S
b11100 /
b11100 X
b11100 f
1$
#95000
0$
#100000
b1111 Q
b1111 c
b101 O
b101 Z
b1010 !
b1010 *
b1010 H
b1010 N
b1010 d
b1111 #
b1111 3
b1111 I
b1111 W
b1111 \
b101 V
b101 _
b11 5
b11 >
b11 B
b11 J
b11 Y
b1010000111001001 ^
b1001 b
b101 a
b110 6
b110 ?
b100100 T
b10100001110010010010011 1
b10100001110010010010011 U
b10100001110010010010011 g
b100100 S
b100101 R
b100000 /
b100000 X
b100000 f
1$
#105000
0$
#110000
b1 Q
b1 c
b10100 O
b10100 Z
bx !
bx *
bx H
bx N
bx d
0)
b1 #
b1 3
b1 I
b1 W
b1 \
b10100 V
b10100 _
b101 5
b101 >
b101 B
b101 J
b101 Y
b101000000101001010 ^
b1010 b
b10100 a
b10 6
b10 ?
b101000 T
b1010000001010010100010011 1
b1010000001010010100010011 U
b1010000001010010100010011 g
b101000 S
b111000 R
b100100 /
b100100 X
b100100 f
1$
#115000
0$
#120000
bx Q
bx c
b1100100 #
b1100100 3
b1100100 I
b1100100 W
b1100100 \
bx +
bx M
b1100100 O
b1100100 Z
b1010 !
b1010 *
b1010 H
b1010 N
b1010 d
b0 P
b0 [
b0 e
b0 5
b0 >
b0 B
b0 J
b0 Y
x:
x9
b1100100 V
b1100100 _
1@
b0 =
b0 A
b0 D
bx F
1"
b1 2
b1 ;
b1 E
b1 K
b1 ]
0,
b11000010000001000100 ^
b100 b
b1 a
b0 `
b100011 8
b100011 C
b101100 T
b110000100000010001000100011 1
b110000100000010001000100011 U
b110000100000010001000100011 g
b101100 S
b10001100 R
b101000 /
b101000 X
b101000 f
1$
#125000
0$
#130000
b1101000 #
b1101000 3
b1101000 I
b1101000 W
b1101000 \
b1101000 O
b1101000 Z
b1111 !
b1111 *
b1111 H
b1111 N
b1111 d
b1101000 V
b1101000 _
b11000100000001001000 ^
b1000 b
b10 a
b110000 T
b110001000000010010000100011 1
b110001000000010010000100011 U
b110001000000010010000100011 g
bx -
bx G
bx L
b110000 S
b10010100 R
b101100 /
b101100 X
b101100 f
1$
#135000
0$
#140000
b1101100 #
b1101100 3
b1101100 I
b1101100 W
b1101100 \
b1101100 O
b1101100 Z
b11001 !
b11001 *
b11001 H
b11001 N
b11001 d
b1101100 V
b1101100 _
b11000110000001001100 ^
b1100 b
b11 a
b110100 T
b110001100000010011000100011 1
b110001100000010011000100011 U
b110001100000010011000100011 g
bx -
bx G
bx L
b110100 S
b10011100 R
b110000 /
b110000 X
b110000 f
1$
#145000
0$
#150000
b1110000 #
b1110000 3
b1110000 I
b1110000 W
b1110000 \
b1110000 O
b1110000 Z
b101 !
b101 *
b101 H
b101 N
b101 d
b1110000 V
b1110000 _
b11001000000001010000 ^
b10000 b
b100 a
b111000 T
b110010000000010100000100011 1
b110010000000010100000100011 U
b110010000000010100000100011 g
bx -
bx G
bx L
b111000 S
b10100100 R
b110100 /
b110100 X
b110100 f
1$
#155000
0$
#160000
b1110100 #
b1110100 3
b1110100 I
b1110100 W
b1110100 \
b1110100 O
b1110100 Z
b1010 !
b1010 *
b1010 H
b1010 N
b1010 d
b1110100 V
b1110100 _
b11001010000001010100 ^
b10100 b
b101 a
b111100 T
b110010100000010101000100011 1
b110010100000010101000100011 U
b110010100000010101000100011 g
bx -
bx G
bx L
b111100 S
b10101100 R
b111000 /
b111000 X
b111000 f
1$
#165000
0$
#170000
b1111000 #
b1111000 3
b1111000 I
b1111000 W
b1111000 \
b1111000 O
b1111000 Z
b1111 !
b1111 *
b1111 H
b1111 N
b1111 d
b1111000 V
b1111000 _
b11001100000001011000 ^
b11000 b
b110 a
b1000000 T
b110011000000010110000100011 1
b110011000000010110000100011 U
b110011000000010110000100011 g
bx -
bx G
bx L
b1000000 S
b10110100 R
b111100 /
b111100 X
b111100 f
1$
#175000
0$
#180000
b1111100 #
b1111100 3
b1111100 I
b1111100 W
b1111100 \
b1111100 O
b1111100 Z
b1 !
b1 *
b1 H
b1 N
b1 d
b1111100 V
b1111100 _
b11001110000001011100 ^
b11100 b
b111 a
b1000100 T
b110011100000010111000100011 1
b110011100000010111000100011 U
b110011100000010111000100011 g
bx -
bx G
bx L
b1000100 S
b10111100 R
b1000000 /
b1000000 X
b1000000 f
1$
#185000
0$
#190000
b10000000 #
b10000000 3
b10000000 I
b10000000 W
b10000000 \
b10000000 O
b10000000 Z
b10 !
b10 *
b10 H
b10 N
b10 d
b10000000 V
b10000000 _
b100010000000001000000 ^
b0 b
b1000 a
b1001000 T
b1000100000000010000000100011 1
b1000100000000010000000100011 U
b1000100000000010000000100011 g
bx -
bx G
bx L
b1001000 S
b11000100 R
b1000100 /
b1000100 X
b1000100 f
1$
#195000
0$
#200000
b10000100 #
b10000100 3
b10000100 I
b10000100 W
b10000100 \
b10000100 O
b10000100 Z
b1111 !
b1111 *
b1111 H
b1111 N
b1111 d
b10000100 V
b10000100 _
b100010010000001000100 ^
b100 b
b1001 a
b1001100 T
b1000100100000010001000100011 1
b1000100100000010001000100011 U
b1000100100000010001000100011 g
bx -
bx G
bx L
b1001100 S
b11001100 R
b1001000 /
b1001000 X
b1001000 f
1$
#205000
0$
#210000
b10001000 #
b10001000 3
b10001000 I
b10001000 W
b10001000 \
b10001000 O
b10001000 Z
b1 !
b1 *
b1 H
b1 N
b1 d
b10001000 V
b10001000 _
b100010100000001001000 ^
b1000 b
b1010 a
b1010000 T
b1000101000000010010000100011 1
b1000101000000010010000100011 U
b1000101000000010010000100011 g
bx -
bx G
bx L
b1010000 S
b11010100 R
b1001100 /
b1001100 X
b1001100 f
1$
#215000
0$
#220000
b11001000 #
b11001000 3
b11001000 I
b11001000 W
b11001000 \
b11001000 O
b11001000 Z
b11001 !
b11001 *
b11001 H
b11001 N
b11001 d
b11001000 V
b11001000 _
b110000110000001001000 ^
b11 a
b1010100 T
b1100001100000010010000100011 1
b1100001100000010010000100011 U
b1100001100000010010000100011 g
bx -
bx G
bx L
b1010100 S
b100011000 R
b1010000 /
b1010000 X
b1010000 f
1$
#225000
0$
#230000
b11001 Q
b11001 c
b1 +
b1 M
b10 !
b10 *
b10 H
b10 N
b10 d
1:
09
0@
b1 F
0"
b0 2
b0 ;
b0 E
b0 K
b0 ]
1,
b110010000000001001011 ^
b1011 b
b1000 a
b11 8
b11 C
b1011000 T
b1100100000000010010110000011 1
b1100100000000010010110000011 U
b1100100000000010010110000011 g
b11001 -
b11001 G
b11001 L
b1011000 S
b100011100 R
b1010100 /
b1010100 X
b1010100 f
1$
#235000
0$
#240000
bx -
bx G
bx L
bx Q
bx c
b10001100 #
b10001100 3
b10001100 I
b10001100 W
b10001100 \
bx +
bx M
b10001100 O
b10001100 Z
b11001 !
b11001 *
b11001 H
b11001 N
b11001 d
x:
x9
b10001100 V
b10001100 _
1@
bx F
1"
b1 2
b1 ;
b1 E
b1 K
b1 ]
0,
b100010110000001001100 ^
b1100 b
b1011 a
b100011 8
b100011 C
b1011100 T
b1000101100000010011000100011 1
b1000101100000010011000100011 U
b1000101100000010011000100011 g
b1011100 S
b11100100 R
b1011000 /
b1011000 X
b1011000 f
1$
#245000
0$
#250000
b1111 !
b1111 *
b1111 H
b1111 N
b1111 d
b1010 P
b1010 [
b1010 e
b11111111111111111111111111111011 #
b11111111111111111111111111111011 3
b11111111111111111111111111111011 I
b11111111111111111111111111111011 W
b11111111111111111111111111111011 \
b1111 O
b1111 Z
b1000 V
b1000 _
b1 5
b1 >
b1 B
b1 J
b1 Y
b1 =
b1 A
b1 D
1<
0"
04
b10 2
b10 ;
b10 E
b10 K
b10 ]
b100000100001000 ^
b1000 b
b10 a
b1 `
b0 6
b0 ?
b1100011 8
b1100011 C
b1100000 T
b1000001000010001100011 1
b1000001000010001100011 U
b1000001000010001100011 g
bx -
bx G
bx L
b1100000 S
b1100100 R
b1011100 /
b1011100 X
b1011100 f
1$
#255000
0$
#260000
b101010 Q
b101010 c
b0 +
b0 M
b101010 #
b101010 3
b101010 I
b101010 W
b101010 \
b1 !
b1 *
b1 H
b1 N
b1 d
b0 P
b0 [
b0 e
b0 5
b0 >
b0 B
b0 J
b0 Y
0:
09
b101010 O
b101010 Z
b101010 V
b101010 _
0@
b10 =
b10 A
b10 D
0<
b0 F
14
b0 2
b0 ;
b0 E
b0 K
b0 ]
1,
b1010100000000001100 ^
b1100 b
b1010 a
b0 `
b10011 8
b10011 C
b1100100 T
b10101000000000011000010011 1
b10101000000000011000010011 U
b10101000000000011000010011 g
b1100100 S
b10001010 R
b1100000 /
b1100000 X
b1100000 f
1$
#265000
0$
#270000
1.
1)
bx Q
bx c
bx +
bx M
b0 #
b0 3
b0 I
b0 W
b0 \
b0 !
b0 *
b0 H
b0 N
b0 d
b1 5
b1 >
b1 B
b1 J
b1 Y
x:
x9
b0 O
b0 Z
b1000 V
b1000 _
1@
b1 =
b1 A
b1 D
1<
bx F
04
b10 2
b10 ;
b10 E
b10 K
b10 ]
0,
b1000 ^
b1000 b
b0 a
b1100011 8
b1100011 C
b1101100 T
b10001100011 1
b10001100011 U
b10001100011 g
b1101000 S
b1101100 R
b1100100 /
b1100100 X
b1100100 f
1$
#275000
0$
