Q3/dmem.v
module dmem (
    input clk, we,
    input [31:0] a, wd,
    output [31:0] rd
);
    reg [31:0] RAM[0:63]; // 64-word memory

    assign rd = RAM[a[31:2]];

    always @(posedge clk) begin
        if (we) RAM[a[31:2]] <= wd;
    end
endmodule

Q1/imem.v
module imem (
    input [31:0] a,
    output [31:0] rd
);
    reg [31:0] ROM[0:63];

    initial begin
        $readmemh("memfile.hex", ROM);
    end

    assign rd = ROM[a[31:2]];
endmodule

Q2/alu.v
module alu (
    input [31:0] a, b,
    input [2:0] alucontrol,
    output reg [31:0] result,
    output zero
);
    always @(*) begin
        case (alucontrol)
            3'b000: result = a + b;
            3'b001: result = a - b;
            3'b010: result = a & b;
            3'b011: result = a | b;
            3'b101: result = ($signed(a) < $signed(b)) ? 32'd1 : 32'd0; // slt
            3'b100: result = $signed(a) >>> b[4:0]; // sra
            default: result = 32'bx;
        endcase
    end
    assign zero = (result == 32'b0);
endmodule

Q2/extend.v
module extend (
    input [31:7] instr,
    input [1:0] immsrc,
    output reg [31:0] immext
);
    always @(*) begin
        case (immsrc)
            2'b00: immext = {{20{instr[31]}}, instr[31:20]}; // I-type
            2'b01: immext = {{20{instr[31]}}, instr[31:25], instr[11:7]}; // S-type
            2'b10: immext = {{20{instr[31]}}, instr[7], instr[30:25], instr[11:8], 1'b0}; // B-type
            2'b11: immext = {{12{instr[31]}}, instr[19:12], instr[20], instr[30:21], 1'b0}; // J-type
            default: immext = 32'bx;
        endcase
    end
endmodule

Q3/regfile.v
module regfile (
    input clk,
    input we3,
    input [4:0] a1, a2, a3,
    input [31:0] wd3,
    output [31:0] rd1, rd2
);
    reg [31:0] rf[31:0];

    always @(posedge clk) begin
        if (we3 && a3 != 0) rf[a3] <= wd3;
    end

    assign rd1 = (a1 != 0) ? rf[a1] : 32'b0;
    assign rd2 = (a2 != 0) ? rf[a2] : 32'b0;
endmodule

Q2/datapath.v
module datapath (
    input clk, reset,
    input [1:0] resultsrc,
    input pcsrc, alusrc,
    input regwrite,
    input [1:0] immsrc,
    input [2:0] alucontrol,
    output zero,
    output reg [31:0] pc,
    input [31:0] instr,
    output [31:0] aluout, writedata,
    input [31:0] readdata
);
    wire [31:0] pcnext, pcplus4, pctarget;
    wire [31:0] immext;
    wire [31:0] srca, srcb;
    wire [31:0] result;

    assign pcplus4 = pc + 4;
    assign pctarget = pc + immext;
    assign pcnext = pcsrc ? pctarget : pcplus4;

    always @(posedge clk or posedge reset) begin
        if (reset) pc <= 32'b0;
        else pc <= pcnext;
    end

    regfile rf (
        .clk(clk),
        .we3(regwrite),
        .a1(instr[19:15]),
        .a2(instr[24:20]),
        .a3(instr[11:7]),
        .wd3(result),
        .rd1(srca),
        .rd2(writedata)
    );

    extend ext (
        .instr(instr[31:7]),
        .immsrc(immsrc),
        .immext(immext)
    );

    assign srcb = alusrc ? immext : writedata;

    alu alu_inst (
        .a(srca),
        .b(srcb),
        .alucontrol(alucontrol),
        .result(aluout),
        .zero(zero)
    );

    assign result = (resultsrc == 2'b00) ? aluout :
                    (resultsrc == 2'b01) ? readdata :
                    (resultsrc == 2'b10) ? pcplus4 : 32'bx;

endmodule

Q2/controller.v
module controller (
    input [6:0] op,
    input [2:0] funct3,
    input funct7_5,
    input zero,
    output resultsrc_0, resultsrc_1,
    output memwrite,
    output pcsrc, alusrc,
    output regwrite, jump,
    output [1:0] immsrc,
    output [2:0] alucontrol
);
    wire [1:0] aluop;
    wire branch;
    
    maindec md (
        .op(op),
        .resultsrc({resultsrc_1, resultsrc_0}),
        .memwrite(memwrite),
        .branch(branch),
        .alusrc(alusrc),
        .regwrite(regwrite),
        .jump(jump),
        .immsrc(immsrc),
        .aluop(aluop)
    );
    
    aludec ad (
        .opb5(op[5]),
        .funct3(funct3),
        .funct7_5(funct7_5),
        .aluop(aluop),
        .alucontrol(alucontrol)
    );
    
    assign pcsrc = jump | (branch & zero);
endmodule

module maindec (
    input [6:0] op,
    output reg [1:0] resultsrc,
    output reg memwrite,
    output reg branch,
    output reg alusrc,
    output reg regwrite,
    output reg jump,
    output reg [1:0] immsrc,
    output reg [1:0] aluop
);
    always @(*) begin
        case (op)
            7'b0000011: begin // lw
                regwrite = 1; immsrc = 2'b00; alusrc = 1; memwrite = 0;
                resultsrc = 2'b01; branch = 0; aluop = 2'b00; jump = 0;
            end
            7'b0100011: begin // sw
                regwrite = 0; immsrc = 2'b01; alusrc = 1; memwrite = 1;
                resultsrc = 2'bxx; branch = 0; aluop = 2'b00; jump = 0;
            end
            7'b0110011: begin // R-type
                regwrite = 1; immsrc = 2'bxx; alusrc = 0; memwrite = 0;
                resultsrc = 2'b00; branch = 0; aluop = 2'b10; jump = 0;
            end
            7'b1100011: begin // beq
                regwrite = 0; immsrc = 2'b10; alusrc = 0; memwrite = 0;
                resultsrc = 2'bxx; branch = 1; aluop = 2'b01; jump = 0;
            end
            7'b0010011: begin // I-type ALU
                regwrite = 1; immsrc = 2'b00; alusrc = 1; memwrite = 0;
                resultsrc = 2'b00; branch = 0; aluop = 2'b10; jump = 0; 
            end
            7'b1101111: begin // jal
                regwrite = 1; immsrc = 2'b11; alusrc = 1'bx; memwrite = 0;
                resultsrc = 2'b10; branch = 0; aluop = 2'bxx; jump = 1;
            end
            default: begin
                regwrite = 0; immsrc = 2'b00; alusrc = 0; memwrite = 0;
                resultsrc = 2'b00; branch = 0; aluop = 2'b00; jump = 0;
            end
        endcase
    end
endmodule

module aludec (
    input opb5,
    input [2:0] funct3,
    input funct7_5,
    input [1:0] aluop,
    output reg [2:0] alucontrol
);
    always @(*) begin
        case (aluop)
            2'b00: alucontrol = 3'b000; // add
            2'b01: alucontrol = 3'b001; // sub
            2'b10: begin // R-type or I-type ALU
                case (funct3)
                    3'b000: begin
                        if ({opb5, funct7_5} == 2'b11) alucontrol = 3'b001; // sub
                        else alucontrol = 3'b000; // add
                    end
                    3'b010: alucontrol = 3'b101; // slt, slti
                    3'b110: alucontrol = 3'b011; // or, ori
                    3'b111: alucontrol = 3'b010; // and, andi
                    3'b101: begin
                        if (funct7_5) alucontrol = 3'b100; // srai
                        else alucontrol = 3'bxxx;
                    end
                    default: alucontrol = 3'bxxx;
                endcase
            end
            default: alucontrol = 3'bxxx;
        endcase
    end
endmodule

Q2/riscv_core.v
module riscv_core (
    input clk, reset,
    output [31:0] writedata, dataadr,
    output memwrite
);
    wire [31:0] pc, instr, readdata;
    wire [1:0] resultsrc;
    wire pcsrc, alusrc, regwrite, jump, zero;
    wire [1:0] immsrc;
    wire [2:0] alucontrol;

    controller c (
        .op(instr[6:0]),
        .funct3(instr[14:12]),
        .funct7_5(instr[30]),
        .zero(zero),
        .resultsrc_0(resultsrc[0]),
        .resultsrc_1(resultsrc[1]),
        .memwrite(memwrite),
        .pcsrc(pcsrc),
        .alusrc(alusrc),
        .regwrite(regwrite),
        .jump(jump),
        .immsrc(immsrc),
        .alucontrol(alucontrol)
    );

    datapath dp (
        .clk(clk),
        .reset(reset),
        .resultsrc(resultsrc),
        .pcsrc(pcsrc),
        .alusrc(alusrc),
        .regwrite(regwrite),
        .immsrc(immsrc),
        .alucontrol(alucontrol),
        .zero(zero),
        .pc(pc),
        .instr(instr),
        .aluout(dataadr),
        .writedata(writedata),
        .readdata(readdata)
    );

    imem imem_inst (
        .a(pc),
        .rd(instr)
    );

    dmem dmem_inst (
        .clk(clk),
        .we(memwrite),
        .a(dataadr),
        .wd(writedata),
        .rd(readdata)
    );
endmodule

Q2/tb_q2.v
`timescale 1ns/1ps

module tb_q2;
    reg clk;
    reg reset;
    wire [31:0] writedata, dataadr;
    wire memwrite;

    riscv_core dut (
        .clk(clk),
        .reset(reset),
        .writedata(writedata),
        .dataadr(dataadr),
        .memwrite(memwrite)
    );

    initial begin
        $dumpfile("tb_q2.vcd");
        $dumpvars(0, tb_q2);
        reset <= 1;
        #22; reset <= 0;
        #200;
        
        $display("Checking Q2 Results (srai test):");
        if (dut.dmem_inst.RAM[100/4] === 32'hfffffffc) begin
            $display("  [PASS] srai (negative): dmem[100] = -4");
        end else begin
            $display("  [FAIL] srai (negative): dmem[100] = %h (expected fffffffc)", dut.dmem_inst.RAM[100/4]);
        end

        if (dut.dmem_inst.RAM[104/4] === 32'd4) begin
            $display("  [PASS] srai (positive): dmem[104] = 4");
        end else begin
            $display("  [FAIL] srai (positive): dmem[104] = %d (expected 4)", dut.dmem_inst.RAM[104/4]);
        end

        $finish;
    end

    always begin
        clk <= 1; #5; clk <= 0; #5;
    end

    always @(negedge clk) begin
        if (memwrite) begin
            $display("  [WRITE] cycle=%0t : MEM[0x%08h] <= 0x%08h", $time, dataadr, writedata);
        end
    end
endmodule

Q2/tb_q2.vcd
$date
	Thu Apr 30 12:50:13 2026
$end
$version
	Icarus Verilog
$end
$timescale
	1ps
$end
$scope module tb_q2 $end
$var wire 32 ! writedata [31:0] $end
$var wire 1 " memwrite $end
$var wire 32 # dataadr [31:0] $end
$var reg 1 $ clk $end
$var reg 1 % reset $end
$scope module dut $end
$var wire 1 $ clk $end
$var wire 1 % reset $end
$var wire 1 & zero $end
$var wire 32 ' writedata [31:0] $end
$var wire 2 ( resultsrc [1:0] $end
$var wire 1 ) regwrite $end
$var wire 32 * readdata [31:0] $end
$var wire 1 + pcsrc $end
$var wire 32 , pc [31:0] $end
$var wire 1 " memwrite $end
$var wire 1 - jump $end
$var wire 32 . instr [31:0] $end
$var wire 2 / immsrc [1:0] $end
$var wire 32 0 dataadr [31:0] $end
$var wire 1 1 alusrc $end
$var wire 3 2 alucontrol [2:0] $end
$scope module c $end
$var wire 3 3 funct3 [2:0] $end
$var wire 1 4 funct7_5 $end
$var wire 7 5 op [6:0] $end
$var wire 1 + pcsrc $end
$var wire 1 & zero $end
$var wire 1 6 resultsrc_1 $end
$var wire 1 7 resultsrc_0 $end
$var wire 1 ) regwrite $end
$var wire 1 " memwrite $end
$var wire 1 - jump $end
$var wire 2 8 immsrc [1:0] $end
$var wire 1 9 branch $end
$var wire 1 1 alusrc $end
$var wire 2 : aluop [1:0] $end
$var wire 3 ; alucontrol [2:0] $end
$scope module ad $end
$var wire 3 < funct3 [2:0] $end
$var wire 1 4 funct7_5 $end
$var wire 1 = opb5 $end
$var wire 2 > aluop [1:0] $end
$var reg 3 ? alucontrol [2:0] $end
$upscope $end
$scope module md $end
$var wire 7 @ op [6:0] $end
$var reg 2 A aluop [1:0] $end
$var reg 1 1 alusrc $end
$var reg 1 9 branch $end
$var reg 2 B immsrc [1:0] $end
$var reg 1 - jump $end
$var reg 1 " memwrite $end
$var reg 1 ) regwrite $end
$var reg 2 C resultsrc [1:0] $end
$upscope $end
$upscope $end
$scope module dmem_inst $end
$var wire 1 $ clk $end
$var wire 32 D rd [31:0] $end
$var wire 1 " we $end
$var wire 32 E wd [31:0] $end
$var wire 32 F a [31:0] $end
$upscope $end
$scope module dp $end
$var wire 3 G alucontrol [2:0] $end
$var wire 1 1 alusrc $end
$var wire 1 $ clk $end
$var wire 2 H immsrc [1:0] $end
$var wire 1 + pcsrc $end
$var wire 32 I readdata [31:0] $end
$var wire 1 ) regwrite $end
$var wire 1 % reset $end
$var wire 2 J resultsrc [1:0] $end
$var wire 1 & zero $end
$var wire 32 K writedata [31:0] $end
$var wire 32 L srcb [31:0] $end
$var wire 32 M srca [31:0] $end
$var wire 32 N result [31:0] $end
$var wire 32 O pctarget [31:0] $end
$var wire 32 P pcplus4 [31:0] $end
$var wire 32 Q pcnext [31:0] $end
$var wire 32 R instr [31:0] $end
$var wire 32 S immext [31:0] $end
$var wire 32 T aluout [31:0] $end
$var reg 32 U pc [31:0] $end
$scope module alu_inst $end
$var wire 3 V alucontrol [2:0] $end
$var wire 32 W b [31:0] $end
$var wire 1 & zero $end
$var wire 32 X a [31:0] $end
$var reg 32 Y result [31:0] $end
$upscope $end
$scope module ext $end
$var wire 2 Z immsrc [1:0] $end
$var wire 25 [ instr [31:7] $end
$var reg 32 \ immext [31:0] $end
$upscope $end
$scope module rf $end
$var wire 5 ] a1 [4:0] $end
$var wire 5 ^ a2 [4:0] $end
$var wire 5 _ a3 [4:0] $end
$var wire 1 $ clk $end
$var wire 32 ` wd3 [31:0] $end
$var wire 1 ) we3 $end
$var wire 32 a rd2 [31:0] $end
$var wire 32 b rd1 [31:0] $end
$upscope $end
$upscope $end
$scope module imem_inst $end
$var wire 32 c a [31:0] $end
$var wire 32 d rd [31:0] $end
$upscope $end
$upscope $end
$upscope $end
$enddefinitions $end
$comment Show the parameter values. $end
$dumpall
$end
#0
$dumpvars
b11111111000000000000000010010011 d
b0 c
b0 b
bx a
b11111111111111111111111111110000 `
b1 _
b10000 ^
b0 ]
b11111111111111111111111111110000 \
b1111111100000000000000001 [
b0 Z
b11111111111111111111111111110000 Y
b0 X
b11111111111111111111111111110000 W
b0 V
b0 U
b11111111111111111111111111110000 T
b11111111111111111111111111110000 S
b11111111000000000000000010010011 R
b100 Q
b100 P
b11111111111111111111111111110000 O
b11111111111111111111111111110000 N
b0 M
b11111111111111111111111111110000 L
bx K
b0 J
bx I
b0 H
b0 G
b11111111111111111111111111110000 F
bx E
bx D
b0 C
b0 B
b10 A
b10011 @
b0 ?
b10 >
0=
b0 <
b0 ;
b10 :
09
b0 8
07
06
b10011 5
14
b0 3
b0 2
11
b11111111111111111111111111110000 0
b0 /
b11111111000000000000000010010011 .
0-
b0 ,
0+
bx *
1)
b0 (
bx '
0&
1%
1$
b11111111111111111111111111110000 #
0"
bx !
$end
#5000
0$
#10000
1$
#15000
0$
#20000
1$
#22000
0%
#25000
0$
#30000
b11111111111111111111111111111100 N
b11111111111111111111111111111100 `
b10000000010 L
b10000000010 W
b11111111111111111111111111110000 M
b11111111111111111111111111110000 X
b11111111111111111111111111110000 b
0&
b11111111111111111111111111111100 #
b11111111111111111111111111111100 0
b11111111111111111111111111111100 F
b11111111111111111111111111111100 T
b11111111111111111111111111111100 Y
b10000000010 S
b10000000010 \
b100 2
b100 ;
b100 ?
b100 G
b100 V
b100000000100000110100010 [
b10 _
b10 ^
b1 ]
b101 3
b101 <
b1000 Q
b1000000001000001101000100010011 .
b1000000001000001101000100010011 R
b1000000001000001101000100010011 d
b1000 P
b10000000110 O
b100 ,
b100 U
b100 c
1$
#35000
0$
#40000
bx N
bx `
bx (
bx J
b1100100 L
b1100100 W
b0 M
b0 X
b0 b
b1100100 #
b1100100 0
b1100100 F
b1100100 T
b1100100 Y
x7
x6
b1100100 S
b1100100 \
b0 2
b0 ;
b0 ?
b0 G
b0 V
1=
b0 :
b0 >
b0 A
bx C
1"
b1 /
b1 8
b1 B
b1 H
b1 Z
0)
b11000100000001000100 [
b100 _
b0 ]
04
b10 3
b10 <
b100011 5
b100011 @
b11111111111111111111111111111100 !
b11111111111111111111111111111100 '
b11111111111111111111111111111100 E
b11111111111111111111111111111100 K
b11111111111111111111111111111100 a
b1100 Q
b110001000000010001000100011 .
b110001000000010001000100011 R
b110001000000010001000100011 d
b1100 P
b1101100 O
b1000 ,
b1000 U
b1000 c
1$
#45000
0$
#50000
b10000 N
b10000 `
b10000 #
b10000 0
b10000 F
b10000 T
b10000 Y
b0 (
b0 J
b10000 L
b10000 W
bx !
bx '
bx E
bx K
bx a
07
06
b10000 S
b10000 \
0=
b10 :
b10 >
b10 A
b0 C
0"
b0 /
b0 8
b0 B
b0 H
b0 Z
1)
b100000000000000011 [
b11 _
b10000 ^
b0 3
b0 <
b10011 5
b10011 @
b10000 Q
b1000000000000000110010011 .
b1000000000000000110010011 R
b1000000000000000110010011 d
bx *
bx D
bx I
b10000 P
b11100 O
b1100 ,
b1100 U
b1100 c
1$
#55000
0$
#60000
b100 N
b100 `
b10000000010 L
b10000000010 W
b11111111111111111111111111111100 !
b11111111111111111111111111111100 '
b11111111111111111111111111111100 E
b11111111111111111111111111111100 K
b11111111111111111111111111111100 a
b10000 M
b10000 X
b10000 b
0&
b100 #
b100 0
b100 F
b100 T
b100 Y
b10000000010 S
b10000000010 \
b100 2
b100 ;
b100 ?
b100 G
b100 V
b100000000100001110100100 [
b100 _
b10 ^
b11 ]
14
b101 3
b101 <
b10100 Q
b1000000001000011101001000010011 .
b1000000001000011101001000010011 R
b1000000001000011101001000010011 d
b10100 P
b10000010010 O
b10000 ,
b10000 U
b10000 c
1$
#65000
0$
#70000
bx N
bx `
bx (
bx J
b1101000 L
b1101000 W
b100 !
b100 '
b100 E
b100 K
b100 a
b0 M
b0 X
b0 b
b1101000 #
b1101000 0
b1101000 F
b1101000 T
b1101000 Y
x7
x6
b1101000 S
b1101000 \
b0 2
b0 ;
b0 ?
b0 G
b0 V
1=
b0 :
b0 >
b0 A
bx C
1"
b1 /
b1 8
b1 B
b1 H
b1 Z
0)
b11001000000001001000 [
b1000 _
b100 ^
b0 ]
04
b10 3
b10 <
b100011 5
b100011 @
b11000 Q
b110010000000010010000100011 .
b110010000000010010000100011 R
b110010000000010010000100011 d
b11000 P
b1111100 O
b10100 ,
b10100 U
b10100 c
1$
#75000
0$
#80000
1&
b0 N
b0 `
b0 (
b0 J
b0 #
b0 0
b0 F
b0 T
b0 Y
b0 !
b0 '
b0 E
b0 K
b0 a
07
06
b0 L
b0 W
b0 S
b0 \
0=
b0 C
0"
01
b0 /
b0 8
b0 B
b0 H
b0 Z
b0 [
b0 _
b0 ^
b0 3
b0 <
b0 5
b0 @
b11100 Q
b0 .
b0 R
b0 d
bx *
bx D
bx I
b11100 P
b11000 O
b11000 ,
b11000 U
b11000 c
1$
#85000
0$
#90000
b100000 Q
b100000 P
b11100 O
b11100 ,
b11100 U
b11100 c
1$
#95000
0$
#100000
b100100 Q
b100100 P
b100000 O
b100000 ,
b100000 U
b100000 c
1$
#105000
0$
#110000
b101000 Q
b101000 P
b100100 O
b100100 ,
b100100 U
b100100 c
1$
#115000
0$
#120000
b101100 Q
b101100 P
b101000 O
b101000 ,
b101000 U
b101000 c
1$
#125000
0$
#130000
b110000 Q
b110000 P
b101100 O
b101100 ,
b101100 U
b101100 c
1$
#135000
0$
#140000
b110100 Q
b110100 P
b110000 O
b110000 ,
b110000 U
b110000 c
1$
#145000
0$
#150000
b111000 Q
b111000 P
b110100 O
b110100 ,
b110100 U
b110100 c
1$
#155000
0$
#160000
b111100 Q
b111100 P
b111000 O
b111000 ,
b111000 U
b111000 c
1$
#165000
0$
#170000
b1000000 Q
b1000000 P
b111100 O
b111100 ,
b111100 U
b111100 c
1$
#175000
0$
#180000
b1000100 Q
b1000100 P
b1000000 O
b1000000 ,
b1000000 U
b1000000 c
1$
#185000
0$
#190000
b1001000 Q
b1001000 P
b1000100 O
b1000100 ,
b1000100 U
b1000100 c
1$
#195000
0$
#200000
b1001100 Q
b1001100 P
b1001000 O
b1001000 ,
b1001000 U
b1001000 c
1$
#205000
0$
#210000
b1010000 Q
b1010000 P
b1001100 O
b1001100 ,
b1001100 U
b1001100 c
1$
#215000
0$
#220000
b1010100 Q
b1010100 P
b1010000 O
b1010000 ,
b1010000 U
b1010000 c
1$
